bmynab/__init__.py
bmynab/cli.py
bmynab-1.0.0.dist-info/LICENSE
bmynab-1.0.0.dist-info/METADATA
bmynab-1.0.0.dist-info/WHEEL
bmynab-1.0.0.dist-info/entry_points.txt
bmynab-1.0.0.dist-info/top_level.txt
bmynab-1.0.0.dist-info/RECORD
